{
  "parent": "bluepower:item/stone_tile",
  "textures": {
    "bundled_straight_1": "bluepower:blocks/wire/bundled_straight_1",
    "gate": "bluepower:blocks/gates/gate",
    "bundled_connection": "bluepower:blocks/wire/bundled_connection",
    "bundled_side_2": "bluepower:blocks/wire/bundled_side_2",
    "bundled_side_1": "bluepower:blocks/wire/bundled_side_1"
  },
  "display": {
    "gui": {
      "rotation": [ 30, 135, 0 ],
      "translation": [ 0, 2, 0 ],
      "scale": [ 0.8, 0.8, 0.8 ]
    }
  },
  "elements": [
    {
      "name": "Tile",
      "from": [ 3, 0, 3 ],
      "to": [ 13, 3, 13 ],
      "faces": {
        "north": { "texture": "#gate", "uv": [ 3, 1, 13, 3 ] },
        "east": { "texture": "#gate", "uv": [ 2, 4, 12, 6 ] },
        "south": { "texture": "#gate", "uv": [ 2, 7, 12, 9 ] },
        "west": { "texture": "#gate", "uv": [ 2, 6, 12, 8 ] },
        "up": { "texture": "#gate", "uv": [ 2, 2, 12, 12 ] },
        "down": { "texture": "#gate", "uv": [ 2, 2, 12, 12 ] }
      }
    },
    {
      "name": "Cube",
      "from": [ 5, 3, 3 ],
      "to": [ 11, 5, 13 ],
      "faces": {
        "north": { "texture": "#bundled_connection", "uv": [ 11, 13, 5, 15 ] },
        "east": { "texture": "#bundled_side_2", "uv": [ 1, 13, 15, 15 ] },
        "south": { "texture": "#bundled_connection", "uv": [ 5, 13, 11, 15 ] },
        "west": { "texture": "#bundled_side_1", "uv": [ 1, 13, 15, 15 ] },
        "up": { "texture": "#bundled_straight_1", "uv": [ 5, 0, 11, 14 ] }
      }
    }
  ]
}